README.rst
cakephp_instaweb.py
setup.py
cakephp_instaweb.egg-info/PKG-INFO
cakephp_instaweb.egg-info/SOURCES.txt
cakephp_instaweb.egg-info/dependency_links.txt
cakephp_instaweb.egg-info/entry_points.txt
cakephp_instaweb.egg-info/requires.txt
cakephp_instaweb.egg-info/top_level.txt