Metadata-Version: 1.0
Name: cakephp-instaweb
Version: 0.1
Summary: Instantly serves a CakePHP application
Home-page: http://chris-lamb.co.uk/projects/cakephp-instaweb/
Author: Chris Lamb
Author-email: chris@chris-lamb.co.uk
License: MIT
Platform: UNKNOWN
